depthcharge/__init__.py
depthcharge/builtin_payloads.py
depthcharge/cmdline.py
depthcharge/companion.py
depthcharge/console.py
depthcharge/context.py
depthcharge/log.py
depthcharge/monitor.py
depthcharge/operation.py
depthcharge/payload_map.py
depthcharge/progress.py
depthcharge/revcrc32.py
depthcharge/stratagem.py
depthcharge/string.py
depthcharge/version.py
depthcharge/arch/__init__.py
depthcharge/arch/aarch64.py
depthcharge/arch/arch.py
depthcharge/arch/arm.py
depthcharge/arch/generic.py
depthcharge/checker/__init__.py
depthcharge/checker/config_checker.py
depthcharge/checker/report.py
depthcharge/checker/security_risk.py
depthcharge/checker/uboot_config.py
depthcharge/checker/uboot_header.py
depthcharge/checker/_builtins/__init__.py
depthcharge/checker/_builtins/arch.py
depthcharge/checker/_builtins/cmdline.py
depthcharge/checker/_builtins/env.py
depthcharge/checker/_builtins/fit.py
depthcharge/checker/_builtins/fs.py
depthcharge/checker/_builtins/lib.py
depthcharge/checker/_builtins/net.py
depthcharge/checker/_builtins/usb.py
depthcharge/executor/__init__.py
depthcharge/executor/executor.py
depthcharge/executor/go.py
depthcharge/hunter/__init__.py
depthcharge/hunter/cmdtbl.py
depthcharge/hunter/constant.py
depthcharge/hunter/cp.py
depthcharge/hunter/env.py
depthcharge/hunter/fdt.py
depthcharge/hunter/hunter.py
depthcharge/hunter/revcrc32.py
depthcharge/hunter/string.py
depthcharge/memory/__init__.py
depthcharge/memory/cp.py
depthcharge/memory/crc32.py
depthcharge/memory/data_abort.py
depthcharge/memory/go.py
depthcharge/memory/i2c.py
depthcharge/memory/itest.py
depthcharge/memory/load.py
depthcharge/memory/memcmds.py
depthcharge/memory/patch.py
depthcharge/memory/reader.py
depthcharge/memory/setexpr.py
depthcharge/memory/stratagem.py
depthcharge/memory/writer.py
depthcharge/register/__init__.py
depthcharge/register/cp.py
depthcharge/register/crc32.py
depthcharge/register/data_abort.py
depthcharge/register/fdt.py
depthcharge/register/itest.py
depthcharge-0.5.0.dist-info/METADATA
depthcharge-0.5.0.dist-info/WHEEL
depthcharge-0.5.0.dist-info/top_level.txt
depthcharge-0.5.0.dist-info/RECORD
