Metadata-Version: 2.1
Name: depthcharge
Version: 0.5.0
Summary: A U-Boot toolkit for security researchers and tinkerers
Home-page: https://github.com/nccgroup/depthcharge
Author: Jon Szymaniak (NCC Group)
Author-email: jon.szymaniak.foss@gmail.com
License: BSD 3-Clause License
Project-URL: Documentation, https://depthcharge.readthedocs.io
Project-URL: Source, https://github.com/nccgroup/depthcharge
Project-URL: Issue Tracker, https://github.com/nccgroup/depthcharge/issues
Classifier: Development Status :: 4 - Beta
Classifier: Environment :: Console
Classifier: Intended Audience :: Other Audience
Classifier: License :: OSI Approved :: BSD License
Classifier: Operating System :: POSIX :: Linux
Classifier: Programming Language :: Python :: 3 :: Only
Classifier: Programming Language :: Python :: 3.6
Classifier: Programming Language :: Python :: 3.7
Classifier: Programming Language :: Python :: 3.8
Classifier: Topic :: Security
Classifier: Topic :: System :: Boot
Classifier: Topic :: System :: Hardware
Requires-Python: >=3.6, <4
Requires-Dist: pyserial (>=3.4)
Requires-Dist: tqdm (>=4.30.0)
Provides-Extra: docs
Requires-Dist: sphinx (>=4.4.0) ; extra == 'docs'
Requires-Dist: sphinx-rtd-theme (<2.0.0,>=1.0.0) ; extra == 'docs'
